Metadata-Version: 2.1
Name: django-translations
Version: 1.4.3
Summary: Django model translation for perfectionists with deadlines.
Home-page: https://github.com/bbmokhtari/django-translations
Author: Behzad B. Mokhtari
Author-email: bbmokhtari.global@gmail.com
Project-URL: Documentation, https://bbmokhtari.github.io/django-translations
Project-URL: Funding, https://bbmokhtari.github.io/django-translations/donation.html
Project-URL: Source, https://github.com/bbmokhtari/django-translations
Project-URL: Tracker, https://github.com/bbmokhtari/django-translations/issues
Keywords: django model translation internationalization localization
Classifier: Development Status :: 6 - Mature
Classifier: Framework :: Django
Classifier: Framework :: Django :: 2.2
Classifier: Framework :: Django :: 3.0
Classifier: Framework :: Django :: 3.1
Classifier: Framework :: Django :: 3.2
Classifier: Framework :: Django :: 4.0
Classifier: Framework :: Django :: 4.1
Classifier: Framework :: Django :: 4.2
Classifier: Framework :: Django :: 5.0
Classifier: Framework :: Django :: 5.1
Classifier: Intended Audience :: Developers
Classifier: License :: OSI Approved :: BSD License
Classifier: Natural Language :: English
Classifier: Operating System :: OS Independent
Classifier: Programming Language :: Python :: 3.7
Classifier: Programming Language :: Python :: 3.8
Classifier: Programming Language :: Python :: 3.9
Classifier: Programming Language :: Python :: 3.10
Classifier: Programming Language :: Python :: 3.11
Classifier: Programming Language :: Python :: 3.12
Classifier: Programming Language :: Python :: 3.13
Classifier: Topic :: Software Development :: Internationalization
Requires-Python: >=3.7, <4
License-File: LICENSE
